LICENSE
README.md
setup.cfg
setup.py
cone_commands/__init__.py
cone_commands/__main__.py
cone_commands.egg-info/PKG-INFO
cone_commands.egg-info/SOURCES.txt
cone_commands.egg-info/dependency_links.txt
cone_commands.egg-info/entry_points.txt
cone_commands.egg-info/not-zip-safe
cone_commands.egg-info/requires.txt
cone_commands.egg-info/top_level.txt
cone_commands/conf/__init__.py
cone_commands/conf/global_settings.py
cone_commands/contrib/__init__.py
cone_commands/contrib/dingtalk/__init__.py
cone_commands/contrib/dingtalk/robot.py
cone_commands/contrib/json_tool/__init__.py
cone_commands/contrib/json_tool/json_tool.py
cone_commands/contrib/myip/__init__.py
cone_commands/contrib/myip/myip.py
cone_commands/contrib/password/__init__.py
cone_commands/contrib/password/password.py
cone_commands/contrib/stock/__init__.py
cone_commands/contrib/stock/base.py
cone_commands/contrib/stock/stock.py
cone_commands/contrib/stock/data_source/__init__.py
cone_commands/contrib/stock/data_source/xueqiu.py
cone_commands/contrib/stock/receiver/__init__.py
cone_commands/contrib/stock/receiver/dingtalk.py
cone_commands/contrib/stock/trigger/__init__.py
cone_commands/core/__init__.py
cone_commands/core/status.py
cone_commands/core/management/__init__.py
cone_commands/core/management/base.py
cone_commands/core/management/color.py
cone_commands/core/management/commands/__init__.py
cone_commands/core/management/commands/help.py
cone_commands/core/management/commands/version.py
cone_commands/utils/__init__.py
cone_commands/utils/termcolors.py